qop/__init__.py
qop/base.py
qop/boson.py
qop/fermion.py
qop/grassmann.py
qop/hardcoreboson.py
qop/particle.py
qop/quaternion.py
qop/spin.py
qop/state.py
qop/symbol.py
qop/utils.py
qop/tests/__init__.py
qop/tests/test_boson.py
qop/tests/test_fermion.py
qop/tests/test_grassmann.py
qop/tests/test_hardcoreboson.py
qop/tests/test_mix_string.py
qop/tests/test_quaternion.py
qop/tests/test_spin.py
qop/tests/test_symbol.py
qop-0.0.2.dist-info/LICENSE
qop-0.0.2.dist-info/METADATA
qop-0.0.2.dist-info/WHEEL
qop-0.0.2.dist-info/top_level.txt
qop-0.0.2.dist-info/RECORD
