Metadata-Version: 2.1
Name: qop
Version: 0.0.2
Summary: Make quantum operators and algebras native in python
Home-page: https://github.com/refraction-ray/qop
Author: refraction-ray
Author-email: refraction-ray@protonmail.com
License: UNKNOWN
Platform: UNKNOWN
Classifier: Programming Language :: Python :: 3
Classifier: License :: OSI Approved :: MIT License
Classifier: Operating System :: OS Independent
Requires-Dist: numpy
